pulumi_nomad/__init__.py
pulumi_nomad/_inputs.py
pulumi_nomad/_utilities.py
pulumi_nomad/acl_auth_method.py
pulumi_nomad/acl_binding_rule.py
pulumi_nomad/acl_policy.py
pulumi_nomad/acl_role.py
pulumi_nomad/acl_token.py
pulumi_nomad/csi_volume.py
pulumi_nomad/csi_volume_registration.py
pulumi_nomad/dynamic_host_volume.py
pulumi_nomad/dynamic_host_volume_registration.py
pulumi_nomad/external_volume.py
pulumi_nomad/get_acl_policies.py
pulumi_nomad/get_acl_policy.py
pulumi_nomad/get_acl_role.py
pulumi_nomad/get_acl_roles.py
pulumi_nomad/get_acl_token.py
pulumi_nomad/get_acl_tokens.py
pulumi_nomad/get_allocations.py
pulumi_nomad/get_datacenters.py
pulumi_nomad/get_deployments.py
pulumi_nomad/get_dynamic_host_volume.py
pulumi_nomad/get_job.py
pulumi_nomad/get_job_parser.py
pulumi_nomad/get_jwks.py
pulumi_nomad/get_namespace.py
pulumi_nomad/get_namespaces.py
pulumi_nomad/get_node_pool.py
pulumi_nomad/get_node_pools.py
pulumi_nomad/get_plugin.py
pulumi_nomad/get_plugins.py
pulumi_nomad/get_regions.py
pulumi_nomad/get_scaling_policies.py
pulumi_nomad/get_scaling_policy.py
pulumi_nomad/get_scheduler_policy.py
pulumi_nomad/get_variable.py
pulumi_nomad/get_volumes.py
pulumi_nomad/job.py
pulumi_nomad/namespace.py
pulumi_nomad/node_pool.py
pulumi_nomad/outputs.py
pulumi_nomad/provider.py
pulumi_nomad/pulumi-plugin.json
pulumi_nomad/py.typed
pulumi_nomad/quote_specification.py
pulumi_nomad/scheduler_config.py
pulumi_nomad/sentinel_policy.py
pulumi_nomad/variable.py
pulumi_nomad/volume.py
pulumi_nomad/config/__init__.py
pulumi_nomad/config/__init__.pyi
pulumi_nomad/config/outputs.py
pulumi_nomad/config/vars.py
pulumi_nomad-2.5.4.dist-info/METADATA
pulumi_nomad-2.5.4.dist-info/WHEEL
pulumi_nomad-2.5.4.dist-info/top_level.txt
pulumi_nomad-2.5.4.dist-info/RECORD
